{"v":5,"entries":{"brand-wplogo--docs":{"id":"brand-wplogo--docs","title":"Brand/WpLogo","name":"Docs","importPath":"./src/components/WpLogo/WpLogo.stories.ts","type":"docs","tags":["dev","test","manifest","autodocs"],"storiesImports":[]},"brand-wplogo--horizontal-navy":{"type":"story","subtype":"story","id":"brand-wplogo--horizontal-navy","name":"Horizontal Navy","title":"Brand/WpLogo","importPath":"./src/components/WpLogo/WpLogo.stories.ts","componentPath":"./src/components/WpLogo/WpLogo.vue","tags":["dev","test","manifest","autodocs"],"exportName":"HorizontalNavy"},"brand-wplogo--horizontal-white":{"type":"story","subtype":"story","id":"brand-wplogo--horizontal-white","name":"Horizontal White","title":"Brand/WpLogo","importPath":"./src/components/WpLogo/WpLogo.stories.ts","componentPath":"./src/components/WpLogo/WpLogo.vue","tags":["dev","test","manifest","autodocs"],"exportName":"HorizontalWhite"},"brand-wplogo--vertical-navy":{"type":"story","subtype":"story","id":"brand-wplogo--vertical-navy","name":"Vertical Navy","title":"Brand/WpLogo","importPath":"./src/components/WpLogo/WpLogo.stories.ts","componentPath":"./src/components/WpLogo/WpLogo.vue","tags":["dev","test","manifest","autodocs"],"exportName":"VerticalNavy"},"brand-wplogo--vertical-white":{"type":"story","subtype":"story","id":"brand-wplogo--vertical-white","name":"Vertical White","title":"Brand/WpLogo","importPath":"./src/components/WpLogo/WpLogo.stories.ts","componentPath":"./src/components/WpLogo/WpLogo.vue","tags":["dev","test","manifest","autodocs"],"exportName":"VerticalWhite"},"brand-wplogo--icon-navy":{"type":"story","subtype":"story","id":"brand-wplogo--icon-navy","name":"Icon Navy","title":"Brand/WpLogo","importPath":"./src/components/WpLogo/WpLogo.stories.ts","componentPath":"./src/components/WpLogo/WpLogo.vue","tags":["dev","test","manifest","autodocs"],"exportName":"IconNavy"},"brand-wplogo--icon-white":{"type":"story","subtype":"story","id":"brand-wplogo--icon-white","name":"Icon White","title":"Brand/WpLogo","importPath":"./src/components/WpLogo/WpLogo.stories.ts","componentPath":"./src/components/WpLogo/WpLogo.vue","tags":["dev","test","manifest","autodocs"],"exportName":"IconWhite"},"brand-wplogo--icon-small":{"type":"story","subtype":"story","id":"brand-wplogo--icon-small","name":"Icon — header size (28 px)","title":"Brand/WpLogo","importPath":"./src/components/WpLogo/WpLogo.stories.ts","componentPath":"./src/components/WpLogo/WpLogo.vue","tags":["dev","test","manifest","autodocs"],"exportName":"IconSmall"},"foundations-charte--palette":{"type":"story","subtype":"story","id":"foundations-charte--palette","name":"Palette","title":"Foundations/Charte","importPath":"./src/tokens/Charte.stories.ts","tags":["dev","test","manifest"],"exportName":"Palette"},"foundations-charte--typography":{"type":"story","subtype":"story","id":"foundations-charte--typography","name":"Typography","title":"Foundations/Charte","importPath":"./src/tokens/Charte.stories.ts","tags":["dev","test","manifest"],"exportName":"Typography"},"foundations-charte--spacing-and-radius":{"type":"story","subtype":"story","id":"foundations-charte--spacing-and-radius","name":"Spacing & Radius","title":"Foundations/Charte","importPath":"./src/tokens/Charte.stories.ts","tags":["dev","test","manifest"],"exportName":"SpacingAndRadius"}}}